sniffly/__init__.py
sniffly/__version__.py
sniffly/cli.py
sniffly/config.py
sniffly/server.py
sniffly/share.py
sniffly/api/__init__.py
sniffly/api/data.py
sniffly/api/data_loader.py
sniffly/api/messages.py
sniffly/core/__init__.py
sniffly/core/constants.py
sniffly/core/global_aggregator.py
sniffly/core/processor.py
sniffly/core/stats.py
sniffly/services/__init__.py
sniffly/services/pricing_service.py
sniffly/static/favicon.ico
sniffly/static/css/dashboard.css
sniffly/static/css/date-range-picker.css
sniffly/static/css/project-selector.css
sniffly/static/css/share-modal.css
sniffly/static/images/logo.png
sniffly/static/js/charts.js
sniffly/static/js/commands-tab.js
sniffly/static/js/constants.js
sniffly/static/js/date-range-picker.js
sniffly/static/js/dynamic-interval-chart-builder.js
sniffly/static/js/export.js
sniffly/static/js/jsonl-viewer.js
sniffly/static/js/memory-monitor.js
sniffly/static/js/message-modal.js
sniffly/static/js/messages-tab.js
sniffly/static/js/overview.js
sniffly/static/js/pricing.js
sniffly/static/js/project-detector.js
sniffly/static/js/stats-cards.js
sniffly/static/js/stats.js
sniffly/static/js/utils.js
sniffly/templates/dashboard.html
sniffly/templates/overview.html
sniffly/utils/__init__.py
sniffly/utils/cache_warmer.py
sniffly/utils/local_cache.py
sniffly/utils/log_finder.py
sniffly/utils/logging.py
sniffly/utils/memory_cache.py
sniffly/utils/pricing.py
sniffly-0.1.5.data/data/sniffly/static/favicon.ico
sniffly-0.1.5.data/data/sniffly/static/css/dashboard.css
sniffly-0.1.5.data/data/sniffly/static/css/date-range-picker.css
sniffly-0.1.5.data/data/sniffly/static/css/project-selector.css
sniffly-0.1.5.data/data/sniffly/static/css/share-modal.css
sniffly-0.1.5.data/data/sniffly/static/images/logo.png
sniffly-0.1.5.data/data/sniffly/static/js/charts.js
sniffly-0.1.5.data/data/sniffly/static/js/commands-tab.js
sniffly-0.1.5.data/data/sniffly/static/js/constants.js
sniffly-0.1.5.data/data/sniffly/static/js/date-range-picker.js
sniffly-0.1.5.dist-info/METADATA
sniffly-0.1.5.dist-info/WHEEL
sniffly-0.1.5.dist-info/entry_points.txt
sniffly-0.1.5.dist-info/RECORD
