Metadata-Version: 2.4
Name: sniffly
Version: 0.1.5
Summary: Claude Code Analytics Dashboard
Project-URL: Homepage, https://sniffly.dev
Project-URL: Documentation, https://sniffly.dev/docs
Project-URL: Repository, https://github.com/chiphuyen/sniffly
Project-URL: Issues, https://github.com/chiphuyen/sniffly/issues
Author-email: Chip Huyen <hi@huyenchip.com>
License-Expression: MIT
Classifier: Development Status :: 4 - Beta
Classifier: Intended Audience :: Developers
Classifier: License :: OSI Approved :: MIT License
Classifier: Programming Language :: Python :: 3
Classifier: Programming Language :: Python :: 3.10
Classifier: Programming Language :: Python :: 3.11
Classifier: Programming Language :: Python :: 3.12
Requires-Python: >=3.10
Requires-Dist: aiofiles>=23.0.0
Requires-Dist: boto3>=1.26.0
Requires-Dist: click>=8.0.0
Requires-Dist: fastapi>=0.100.0
Requires-Dist: httpx>=0.24.0
Requires-Dist: orjson>=3.9.0
Requires-Dist: python-dateutil>=2.8.2
Requires-Dist: python-dotenv>=1.0.0
Requires-Dist: python-multipart>=0.0.6
Requires-Dist: uvicorn[standard]>=0.23.0
Requires-Dist: uvloop>=0.17.0; sys_platform != 'win32'
Requires-Dist: winloop>=0.1.8; sys_platform == 'win32'
